{"State.d0dea6a9-c054-4f52-b2ee-e261e7df0bc8": {"id": "d0dea6a9-c054-4f52-b2ee-e261e7df0bc8", "created_at": "2024-03-17T05:41:09.022250", "updated_at": "2024-03-17T05:41:09.022267", "name": "California", "__class__": "State"}, "State.dd20693e-0deb-41d5-b277-77dfceff0f1a": {"id": "dd20693e-0deb-41d5-b277-77dfceff0f1a", "created_at": "2024-03-17T05:41:09.022587", "updated_at": "2024-03-17T05:41:09.022602", "name": "Arizona", "__class__": "State"}, "Place.768c83e2-bc98-478d-bab2-b92f6b14b8a4": {"id": "768c83e2-bc98-478d-bab2-b92f6b14b8a4", "created_at": "2024-03-17T05:41:09.023096", "updated_at": "2024-03-17T05:41:09.023121", "city_id": "0001", "user_id": "0001", "name": "My little house", "number_rooms": 4, "number_bathrooms": 2, "max_guest": 10, "price_by_night": 300, "latitude": 37.773972, "longitude": -122.431297, "__class__": "Place"}}